pyarchops/__init__.py
pyarchops-0.0.5.dist-info/AUTHORS.rst
pyarchops-0.0.5.dist-info/LICENSE
pyarchops-0.0.5.dist-info/METADATA
pyarchops-0.0.5.dist-info/WHEEL
pyarchops-0.0.5.dist-info/top_level.txt
pyarchops-0.0.5.dist-info/RECORD
