Metadata-Version: 2.1
Name: pyarchops
Version: 0.0.5
Summary: Install All pyarchops
Home-page: https://github.com/pyarchops/pyarchops
Author: Azul
Author-email: pyarchops@azulinho.com
License: MIT license
Keywords: pyarchops
Platform: UNKNOWN
Classifier: Development Status :: 2 - Pre-Alpha
Classifier: Intended Audience :: Developers
Classifier: License :: OSI Approved :: MIT License
Classifier: Natural Language :: English
Classifier: Programming Language :: Python :: 3.7
Requires-Dist: ansible (==2.8.0)
Requires-Dist: asn1crypto (==0.24.0)
Requires-Dist: cffi (==1.12.3)
Requires-Dist: cryptography (==2.7)
Requires-Dist: jinja2 (==2.10.1)
Requires-Dist: markupsafe (==1.1.1)
Requires-Dist: pyarchops-dnsmasq (==0.0.2)
Requires-Dist: pyarchops-helpers (==0.0.8)
Requires-Dist: pyarchops-os-updates (==0.0.4)
Requires-Dist: pyarchops-tinc (==0.0.3)
Requires-Dist: pycparser (==2.19)
Requires-Dist: pyyaml (==5.1)
Requires-Dist: six (==1.12.0)
Requires-Dist: suitable (==0.16.0)
